{
  "slug": "bi-an",
  "name": "Bí ẩn",
  "page": 1,
  "totalPages": 3,
  "items": [
    {
      "id": "vought-rising-2027-d5e1e4aa",
      "source": "ophim",
      "slug": "vought-rising",
      "name": "Vought Rising",
      "originName": "Vought Rising",
      "posterUrl": "https://img.ophim.live/uploads/movies/vought-rising-poster.jpg",
      "thumbUrl": "https://img.ophim.live/uploads/movies/vought-rising-thumb.jpg",
      "year": 2027,
      "type": "series",
      "status": "unknown",
      "episodeCurrent": "Trailer",
      "categories": [
        {
          "name": "Hành Động",
          "slug": "hanh-dong"
        },
        {
          "name": "Viễn Tưởng",
          "slug": "vien-tuong"
        },
        {
          "name": "Phiêu Lưu",
          "slug": "phieu-luu"
        },
        {
          "name": "Khoa Học",
          "slug": "khoa-hoc"
        },
        {
          "name": "Bí ẩn",
          "slug": "bi-an"
        }
      ],
      "countries": [
        {
          "name": "Âu Mỹ",
          "slug": "au-my"
        }
      ]
    },
    {
      "id": "movie-2026-55c4d1ef",
      "source": "ophim",
      "slug": "ac-niem",
      "name": "Ác Niệm",
      "originName": "恶念",
      "posterUrl": "https://img.ophim.live/uploads/movies/ac-niem-poster.jpg",
      "thumbUrl": "https://img.ophim.live/uploads/movies/ac-niem-thumb.jpg",
      "year": 2026,
      "type": "single",
      "status": "completed",
      "episodeCurrent": "Full",
      "categories": [
        {
          "name": "Hình Sự",
          "slug": "hinh-su"
        },
        {
          "name": "Bí ẩn",
          "slug": "bi-an"
        }
      ],
      "countries": [
        {
          "name": "Trung Quốc",
          "slug": "trung-quoc"
        }
      ]
    },
    {
      "id": "tagusari-bros-2026-e4f56387",
      "source": "ophim",
      "slug": "tagusari-bros",
      "name": "Anh Em Nhà Tagusari",
      "originName": "TAGUSARI bros.",
      "posterUrl": "https://img.ophim.live/uploads/movies/tagusari-bros-poster.jpg",
      "thumbUrl": "https://img.ophim.live/uploads/movies/tagusari-bros-thumb.jpg",
      "year": 2026,
      "type": "series",
      "status": "ongoing",
      "episodeCurrent": "Tập 9",
      "categories": [
        {
          "name": "Hình Sự",
          "slug": "hinh-su"
        },
        {
          "name": "Bí ẩn",
          "slug": "bi-an"
        }
      ],
      "countries": [
        {
          "name": "Nhật Bản",
          "slug": "nhat-ban"
        }
      ]
    },
    {
      "id": "widow-s-bay-2026-2f767d23",
      "source": "ophim",
      "slug": "bi-an-thi-tran-widows-bay",
      "name": "Bí Ẩn Thị Trấn Widow's Bay",
      "originName": "Widow's Bay",
      "posterUrl": "https://img.ophim.live/uploads/movies/bi-an-thi-tran-widows-bay-poster.jpg",
      "thumbUrl": "https://img.ophim.live/uploads/movies/bi-an-thi-tran-widows-bay-thumb.jpg",
      "year": 2026,
      "type": "series",
      "status": "completed",
      "episodeCurrent": "Hoàn tất (10/10)",
      "categories": [
        {
          "name": "Hài Hước",
          "slug": "hai-huoc"
        },
        {
          "name": "Chính kịch",
          "slug": "chinh-kich"
        },
        {
          "name": "Bí ẩn",
          "slug": "bi-an"
        }
      ],
      "countries": [
        {
          "name": "Âu Mỹ",
          "slug": "au-my"
        }
      ]
    },
    {
      "id": "the-scarecrow-2026-8c7c414e",
      "source": "ophim",
      "slug": "bu-nhin-bong-dem",
      "name": "Bù Nhìn Bóng Đêm",
      "originName": "The Scarecrow",
      "posterUrl": "https://img.ophim.live/uploads/movies/bu-nhin-bong-dem-poster.jpg",
      "thumbUrl": "https://img.ophim.live/uploads/movies/bu-nhin-bong-dem-thumb.jpg",
      "year": 2026,
      "type": "series",
      "status": "completed",
      "episodeCurrent": "Hoàn tất (12/12)",
      "categories": [
        {
          "name": "Hình Sự",
          "slug": "hinh-su"
        },
        {
          "name": "Chính kịch",
          "slug": "chinh-kich"
        },
        {
          "name": "Bí ẩn",
          "slug": "bi-an"
        }
      ],
      "countries": [
        {
          "name": "Hàn Quốc",
          "slug": "han-quoc"
        }
      ]
    },
    {
      "id": "i-will-find-you-2026-8490ce31",
      "source": "ophim",
      "slug": "cha-se-tim-con",
      "name": "Cha sẽ tìm con",
      "originName": "I Will Find You",
      "posterUrl": "https://img.ophim.live/uploads/movies/cha-se-tim-con-poster.jpg",
      "thumbUrl": "https://img.ophim.live/uploads/movies/cha-se-tim-con-thumb.jpg",
      "year": 2026,
      "type": "series",
      "status": "completed",
      "episodeCurrent": "Hoàn tất (8/8)",
      "categories": [
        {
          "name": "Hình Sự",
          "slug": "hinh-su"
        },
        {
          "name": "Chính kịch",
          "slug": "chinh-kich"
        },
        {
          "name": "Bí ẩn",
          "slug": "bi-an"
        }
      ],
      "countries": [
        {
          "name": "Âu Mỹ",
          "slug": "au-my"
        }
      ]
    },
    {
      "id": "classroom-of-the-elite-s-2026-9c495d99",
      "source": "ophim",
      "slug": "chao-mung-den-voi-lop-hoc-de-cao-thuc-luc-phan-4",
      "name": "Chào mừng đến với lớp học đề cao thực lực (Phần 4)",
      "originName": "Classroom of the Elite (Season 4)",
      "posterUrl": "https://img.ophim.live/uploads/movies/chao-mung-den-voi-lop-hoc-de-cao-thuc-luc-phan-4-poster.jpg",
      "thumbUrl": "https://img.ophim.live/uploads/movies/chao-mung-den-voi-lop-hoc-de-cao-thuc-luc-phan-4-thumb.jpg",
      "year": 2026,
      "type": "anime",
      "status": "ongoing",
      "episodeCurrent": "Tập 15",
      "categories": [
        {
          "name": "Chính kịch",
          "slug": "chinh-kich"
        },
        {
          "name": "Bí ẩn",
          "slug": "bi-an"
        }
      ],
      "countries": [
        {
          "name": "Nhật Bản",
          "slug": "nhat-ban"
        },
        {
          "name": "Âu Mỹ",
          "slug": "au-my"
        }
      ]
    },
    {
      "id": "the-terror-season-3-2026-87c13977",
      "source": "ophim",
      "slug": "chuyen-kinh-hoang-phan-3",
      "name": "Chuyện Kinh Hoàng (Phần 3)",
      "originName": "The Terror (Season 3)",
      "posterUrl": "https://img.ophim.live/uploads/movies/chuyen-kinh-hoang-phan-3-poster.jpg",
      "thumbUrl": "https://img.ophim.live/uploads/movies/chuyen-kinh-hoang-phan-3-thumb.jpg",
      "year": 2026,
      "type": "series",
      "status": "completed",
      "episodeCurrent": "Hoàn Tất (6/6)",
      "categories": [
        {
          "name": "Viễn Tưởng",
          "slug": "vien-tuong"
        },
        {
          "name": "Khoa Học",
          "slug": "khoa-hoc"
        },
        {
          "name": "Chính kịch",
          "slug": "chinh-kich"
        },
        {
          "name": "Bí ẩn",
          "slug": "bi-an"
        }
      ],
      "countries": [
        {
          "name": "Âu Mỹ",
          "slug": "au-my"
        }
      ]
    },
    {
      "id": "the-tang-mist-2026-8100a4f9",
      "source": "ophim",
      "slug": "dai-duong-me-vu",
      "name": "Đại Đường Mê Vụ",
      "originName": "The Tang Mist",
      "posterUrl": "https://img.ophim.live/uploads/movies/dai-duong-me-vu-poster.jpg",
      "thumbUrl": "https://img.ophim.live/uploads/movies/dai-duong-me-vu-thumb.jpg",
      "year": 2026,
      "type": "series",
      "status": "completed",
      "episodeCurrent": "Hoàn tất (25/25)",
      "categories": [
        {
          "name": "Chính kịch",
          "slug": "chinh-kich"
        },
        {
          "name": "Bí ẩn",
          "slug": "bi-an"
        }
      ],
      "countries": [
        {
          "name": "Trung Quốc",
          "slug": "trung-quoc"
        }
      ]
    },
    {
      "id": "detective-conan-fallen-a-2026-424e0c62",
      "source": "ophim",
      "slug": "dien-anh-conan-29-thien-than-sa-nga-tren-xa-lo",
      "name": "Điện Ảnh Conan 29 - Thiên Thần Sa Ngã Trên Xa Lộ",
      "originName": "Detective Conan: Fallen Angel of the Highway",
      "posterUrl": "https://img.ophim.live/uploads/movies/dien-anh-conan-29-thien-than-sa-nga-tren-xa-lo-poster.jpg",
      "thumbUrl": "https://img.ophim.live/uploads/movies/dien-anh-conan-29-thien-than-sa-nga-tren-xa-lo-thumb.jpg",
      "year": 2026,
      "type": "anime",
      "status": "unknown",
      "episodeCurrent": "Trailer",
      "categories": [
        {
          "name": "Hành Động",
          "slug": "hanh-dong"
        },
        {
          "name": "Hình Sự",
          "slug": "hinh-su"
        },
        {
          "name": "Bí ẩn",
          "slug": "bi-an"
        }
      ],
      "countries": [
        {
          "name": "Nhật Bản",
          "slug": "nhat-ban"
        }
      ]
    },
    {
      "id": "griya-2026-a6bc9a5e",
      "source": "ophim",
      "slug": "griya",
      "name": "Griya",
      "originName": "Griya",
      "posterUrl": "https://img.ophim.live/uploads/movies/griya-poster.jpg",
      "thumbUrl": "https://img.ophim.live/uploads/movies/griya-thumb.jpg",
      "year": 2026,
      "type": "series",
      "status": "completed",
      "episodeCurrent": "Hoàn tất (10/10)",
      "categories": [
        {
          "name": "Bí ẩn",
          "slug": "bi-an"
        }
      ],
      "countries": [
        {
          "name": "Malaysia",
          "slug": "malaysia"
        }
      ]
    },
    {
      "id": "backrooms-2026-63490990",
      "source": "ophim",
      "slug": "hau-phong-vo-tan",
      "name": "Hậu Phòng Vô Tận",
      "originName": "Backrooms",
      "posterUrl": "https://img.ophim.live/uploads/movies/hau-phong-vo-tan-poster.jpg",
      "thumbUrl": "https://img.ophim.live/uploads/movies/hau-phong-vo-tan-thumb.jpg",
      "year": 2026,
      "type": "single",
      "status": "unknown",
      "episodeCurrent": "Trailer",
      "categories": [
        {
          "name": "Viễn Tưởng",
          "slug": "vien-tuong"
        },
        {
          "name": "Khoa Học",
          "slug": "khoa-hoc"
        },
        {
          "name": "Kinh Dị",
          "slug": "kinh-di"
        },
        {
          "name": "Bí ẩn",
          "slug": "bi-an"
        }
      ],
      "countries": [
        {
          "name": "Âu Mỹ",
          "slug": "au-my"
        },
        {
          "name": "Canada",
          "slug": "canada"
        }
      ]
    },
    {
      "id": "archives-the-nanyang-mys-2026-69875541",
      "source": "ophim",
      "slug": "ho-so-nam-bo",
      "name": "Hồ Sơ Nam Bộ",
      "originName": "Archives: The Nanyang Mystery",
      "posterUrl": "https://img.ophim.live/uploads/movies/ho-so-nam-bo-poster.jpg",
      "thumbUrl": "https://img.ophim.live/uploads/movies/ho-so-nam-bo-thumb.jpg",
      "year": 2026,
      "type": "series",
      "status": "ongoing",
      "episodeCurrent": "Tập 24",
      "categories": [
        {
          "name": "Hành Động",
          "slug": "hanh-dong"
        },
        {
          "name": "Phiêu Lưu",
          "slug": "phieu-luu"
        },
        {
          "name": "Bí ẩn",
          "slug": "bi-an"
        }
      ],
      "countries": [
        {
          "name": "Trung Quốc",
          "slug": "trung-quoc"
        }
      ]
    },
    {
      "id": "reverse-2026-da0ab72d",
      "source": "ophim",
      "slug": "ke-thu-chung-giuong",
      "name": "Kẻ Thù Chung Giường",
      "originName": "Reverse",
      "posterUrl": "https://img.ophim.live/uploads/movies/ke-thu-chung-giuong-poster.jpg",
      "thumbUrl": "https://img.ophim.live/uploads/movies/ke-thu-chung-giuong-thumb.jpg",
      "year": 2026,
      "type": "series",
      "status": "completed",
      "episodeCurrent": "Hoàn tất (8/8)",
      "categories": [
        {
          "name": "Chính kịch",
          "slug": "chinh-kich"
        },
        {
          "name": "Bí ẩn",
          "slug": "bi-an"
        }
      ],
      "countries": [
        {
          "name": "Hàn Quốc",
          "slug": "han-quoc"
        }
      ]
    },
    {
      "id": "killed-again-mr-detectiv-2026-7d567858",
      "source": "ophim",
      "slug": "lai-co-an-mang-nua-roi-thua-tham-tu",
      "name": "Lại Bị Giết Nữa À, Thưa Thám Tử?",
      "originName": "Killed Again, Mr. Detective.",
      "posterUrl": "https://img.ophim.live/uploads/movies/lai-co-an-mang-nua-roi-thua-tham-tu-poster.jpg",
      "thumbUrl": "https://img.ophim.live/uploads/movies/lai-co-an-mang-nua-roi-thua-tham-tu-thumb.jpg",
      "year": 2026,
      "type": "anime",
      "status": "completed",
      "episodeCurrent": "Hoàn tất (12/12)",
      "categories": [
        {
          "name": "Bí ẩn",
          "slug": "bi-an"
        }
      ],
      "countries": [
        {
          "name": "Nhật Bản",
          "slug": "nhat-ban"
        }
      ]
    },
    {
      "id": "loved-one-2026-04f2297a",
      "source": "ophim",
      "slug": "loved-one",
      "name": "LOVED ONE",
      "originName": "LOVED ONE",
      "posterUrl": "https://img.ophim.live/uploads/movies/loved-one-poster.jpg",
      "thumbUrl": "https://img.ophim.live/uploads/movies/loved-one-thumb.jpg",
      "year": 2026,
      "type": "series",
      "status": "ongoing",
      "episodeCurrent": "Tập 7",
      "categories": [
        {
          "name": "Chính kịch",
          "slug": "chinh-kich"
        },
        {
          "name": "Bí ẩn",
          "slug": "bi-an"
        }
      ],
      "countries": [
        {
          "name": "Nhật Bản",
          "slug": "nhat-ban"
        }
      ]
    },
    {
      "id": "missing-2026-6643e9e9",
      "source": "ophim",
      "slug": "mat-trai-cua-mat-tich-ban-thai",
      "name": "Mặt Trái Của Mất Tích (Bản Thái)",
      "originName": "Missing",
      "posterUrl": "https://img.ophim.live/uploads/movies/mat-trai-cua-mat-tich-ban-thai-poster.jpg",
      "thumbUrl": "https://img.ophim.live/uploads/movies/mat-trai-cua-mat-tich-ban-thai-thumb.jpg",
      "year": 2026,
      "type": "series",
      "status": "completed",
      "episodeCurrent": "Hoàn tất (12/12)",
      "categories": [
        {
          "name": "Hình Sự",
          "slug": "hinh-su"
        },
        {
          "name": "Chính kịch",
          "slug": "chinh-kich"
        },
        {
          "name": "Bí ẩn",
          "slug": "bi-an"
        }
      ],
      "countries": [
        {
          "name": "Thái Lan",
          "slug": "thai-lan"
        }
      ]
    },
    {
      "id": "colors-of-evil-black-2026-5251a6f9",
      "source": "ophim",
      "slug": "mau-ta-ac-den",
      "name": "Màu Tà Ác: Đen",
      "originName": "Colors of Evil: Black",
      "posterUrl": "https://img.ophim.live/uploads/movies/mau-ta-ac-den-poster.jpg",
      "thumbUrl": "https://img.ophim.live/uploads/movies/mau-ta-ac-den-thumb.jpg",
      "year": 2026,
      "type": "single",
      "status": "completed",
      "episodeCurrent": "Full",
      "categories": [
        {
          "name": "Hình Sự",
          "slug": "hinh-su"
        },
        {
          "name": "Bí ẩn",
          "slug": "bi-an"
        }
      ],
      "countries": [
        {
          "name": "Ba lan",
          "slug": "ba-lan"
        }
      ]
    },
    {
      "id": "the-gift-2026-808d190d",
      "source": "ophim",
      "slug": "mon-qua-cua-kluay",
      "name": "Món Quà Của Kluay",
      "originName": "The Gift",
      "posterUrl": "https://img.ophim.live/uploads/movies/mon-qua-cua-kluay-poster.jpg",
      "thumbUrl": "https://img.ophim.live/uploads/movies/mon-qua-cua-kluay-thumb.jpg",
      "year": 2026,
      "type": "series",
      "status": "completed",
      "episodeCurrent": "Hoàn tất (34/34)",
      "categories": [
        {
          "name": "Chính kịch",
          "slug": "chinh-kich"
        },
        {
          "name": "Bí ẩn",
          "slug": "bi-an"
        }
      ],
      "countries": [
        {
          "name": "Thái Lan",
          "slug": "thai-lan"
        }
      ]
    },
    {
      "id": "lee-cronin-s-the-mummy-2026-3e65d257",
      "source": "ophim",
      "slug": "xac-uopp",
      "name": "Một bộ phim của Lee Cronin: Xác ướp",
      "originName": "Lee Cronin's The Mummy",
      "posterUrl": "https://img.ophim.live/uploads/movies/xac-uopp-poster.jpg",
      "thumbUrl": "https://img.ophim.live/uploads/movies/xac-uopp-thumb.jpg",
      "year": 2026,
      "type": "single",
      "status": "completed",
      "episodeCurrent": "Full",
      "categories": [
        {
          "name": "Kinh Dị",
          "slug": "kinh-di"
        },
        {
          "name": "Bí ẩn",
          "slug": "bi-an"
        }
      ],
      "countries": [
        {
          "name": "Âu Mỹ",
          "slug": "au-my"
        }
      ]
    },
    {
      "id": "a-good-girl-s-guide-to-m-2026-3c0d564c",
      "source": "ophim",
      "slug": "nhan-chung-cuoi-cung-phan-2",
      "name": "Nhân chứng cuối cùng (Phần 2)",
      "originName": "A Good Girl's Guide to Murder (Season 2)",
      "posterUrl": "https://img.ophim.live/uploads/movies/nhan-chung-cuoi-cung-phan-2-poster.jpg",
      "thumbUrl": "https://img.ophim.live/uploads/movies/nhan-chung-cuoi-cung-phan-2-thumb.jpg",
      "year": 2026,
      "type": "series",
      "status": "completed",
      "episodeCurrent": "Hoàn tất (6/6)",
      "categories": [
        {
          "name": "Hình Sự",
          "slug": "hinh-su"
        },
        {
          "name": "Chính kịch",
          "slug": "chinh-kich"
        },
        {
          "name": "Bí ẩn",
          "slug": "bi-an"
        }
      ],
      "countries": [
        {
          "name": "Anh",
          "slug": "anh"
        },
        {
          "name": "Đức",
          "slug": "duc"
        }
      ]
    },
    {
      "id": "oasis-2026-4c9e29cf",
      "source": "ophim",
      "slug": "oasis-2026",
      "name": "Oasis",
      "originName": "Oasis",
      "posterUrl": "https://img.ophim.live/uploads/movies/oasis-2026-poster.jpg",
      "thumbUrl": "https://img.ophim.live/uploads/movies/oasis-2026-thumb.jpg",
      "year": 2026,
      "type": "series",
      "status": "completed",
      "episodeCurrent": "Hoàn tất (8/8)",
      "categories": [
        {
          "name": "Hình Sự",
          "slug": "hinh-su"
        },
        {
          "name": "Chính kịch",
          "slug": "chinh-kich"
        },
        {
          "name": "Bí ẩn",
          "slug": "bi-an"
        }
      ],
      "countries": [
        {
          "name": "Tây Ban Nha",
          "slug": "tay-ban-nha"
        }
      ]
    },
    {
      "id": "the-boroughs-2026-f03a80f9",
      "source": "ophim",
      "slug": "phien-quan-toc-xam",
      "name": "Phiến Quân Tóc Xám",
      "originName": "The Boroughs",
      "posterUrl": "https://img.ophim.live/uploads/movies/phien-quan-toc-xam-poster.jpg",
      "thumbUrl": "https://img.ophim.live/uploads/movies/phien-quan-toc-xam-thumb.jpg",
      "year": 2026,
      "type": "series",
      "status": "completed",
      "episodeCurrent": "Hoàn tất (8/8)",
      "categories": [
        {
          "name": "Viễn Tưởng",
          "slug": "vien-tuong"
        },
        {
          "name": "Khoa Học",
          "slug": "khoa-hoc"
        },
        {
          "name": "Bí ẩn",
          "slug": "bi-an"
        }
      ],
      "countries": [
        {
          "name": "Âu Mỹ",
          "slug": "au-my"
        }
      ]
    },
    {
      "id": "iron-lung-2026-c2c479a2",
      "source": "ophim",
      "slug": "phoi-sat",
      "name": "Phổi Sắt",
      "originName": "Iron Lung",
      "posterUrl": "https://img.ophim.live/uploads/movies/phoi-sat-poster.jpg",
      "thumbUrl": "https://img.ophim.live/uploads/movies/phoi-sat-thumb.jpg",
      "year": 2026,
      "type": "single",
      "status": "completed",
      "episodeCurrent": "Full",
      "categories": [
        {
          "name": "Viễn Tưởng",
          "slug": "vien-tuong"
        },
        {
          "name": "Khoa Học",
          "slug": "khoa-hoc"
        },
        {
          "name": "Kinh Dị",
          "slug": "kinh-di"
        },
        {
          "name": "Bí ẩn",
          "slug": "bi-an"
        }
      ],
      "countries": [
        {
          "name": "Âu Mỹ",
          "slug": "au-my"
        }
      ]
    }
  ]
}