{
  "id": "fate-chooses-you-2025-028aef70",
  "source": "ophim",
  "slug": "giai-ngau-thien-thanh",
  "name": "Giai Ngẫu Thiên Thành",
  "originName": "Fate Chooses You",
  "posterUrl": "https://img.ophim.live/uploads/movies/giai-ngau-thien-thanh-poster.jpg",
  "thumbUrl": "https://img.ophim.live/uploads/movies/giai-ngau-thien-thanh-thumb.jpg",
  "year": 2025,
  "type": "series",
  "status": "completed",
  "episodeCurrent": "Tập 40",
  "categories": [
    {
      "name": "Viễn Tưởng",
      "slug": "vien-tuong"
    },
    {
      "name": "Khoa Học",
      "slug": "khoa-hoc"
    },
    {
      "name": "Chính kịch",
      "slug": "chinh-kich"
    }
  ],
  "countries": [
    {
      "name": "Trung Quốc",
      "slug": "trung-quoc"
    }
  ],
  "description": "<p>Để phá bỏ lời nguyền mạnh mẽ và cứu lấy gia tộc, Lục Thiên Kiều tái sinh thành người và bí mật kết hôn với Tân Mỹ, một tu sĩ thiên tài mang trong mình lời nguyền định mệnh. Khởi đầu là một nhiệm vụ sinh tồn, họ nhanh chóng vướng vào sự phản bội, mất trí nhớ và tình cảm ngày càng lớn dần khi đối mặt với những thử thách chết người và khám phá ra số phận gắn bó của mình.</p>",
  "quality": "HD",
  "lang": "Vietsub + Thuyết Minh",
  "episodes": [
    {
      "name": "1",
      "slug": "1",
      "serverName": "Vietsub #1",
      "source": "ophim",
      "embedUrl": "https://vip.opstream90.com/share/b453b5a7a737a3fc489fa11aaac1618b",
      "m3u8Url": "https://vip.opstream90.com/20260425/30200_b453b5a7/index.m3u8"
    },
    {
      "name": "2",
      "slug": "2",
      "serverName": "Vietsub #1",
      "source": "ophim",
      "embedUrl": "https://vip.opstream90.com/share/5e5c6be7a4b64ead7fe95a284e013e18",
      "m3u8Url": "https://vip.opstream90.com/20260425/30201_5e5c6be7/index.m3u8"
    },
    {
      "name": "3",
      "slug": "3",
      "serverName": "Vietsub #1",
      "source": "ophim",
      "embedUrl": "https://vip.opstream90.com/share/ac4e368758b1e4e2b89f45b7554ac7ab",
      "m3u8Url": "https://vip.opstream90.com/20260425/30202_ac4e3687/index.m3u8"
    },
    {
      "name": "4",
      "slug": "4",
      "serverName": "Vietsub #1",
      "source": "ophim",
      "embedUrl": "https://vip.opstream90.com/share/bfebf2c52000d2bac1a130520ace5dd7",
      "m3u8Url": "https://vip.opstream90.com/20260425/30203_bfebf2c5/index.m3u8"
    },
    {
      "name": "5",
      "slug": "5",
      "serverName": "Vietsub #1",
      "source": "ophim",
      "embedUrl": "https://vip.opstream90.com/share/4fa0d97504185879b6e7524dda47d98b",
      "m3u8Url": "https://vip.opstream90.com/20260425/30204_4fa0d975/index.m3u8"
    },
    {
      "name": "6",
      "slug": "6",
      "serverName": "Vietsub #1",
      "source": "ophim",
      "embedUrl": "https://vip.opstream90.com/share/122fb7b4ed45d1a1489232864c606b4d",
      "m3u8Url": "https://vip.opstream90.com/20260425/30205_122fb7b4/index.m3u8"
    },
    {
      "name": "7",
      "slug": "7",
      "serverName": "Vietsub #1",
      "source": "ophim",
      "embedUrl": "https://vip.opstream90.com/share/a0318d32cb96f76323313e33d189b3ce",
      "m3u8Url": "https://vip.opstream90.com/20260426/30272_a0318d32/index.m3u8"
    },
    {
      "name": "8",
      "slug": "8",
      "serverName": "Vietsub #1",
      "source": "ophim",
      "embedUrl": "https://vip.opstream90.com/share/5ceda82de78ea91d4c01e536a0673341",
      "m3u8Url": "https://vip.opstream90.com/20260426/30273_5ceda82d/index.m3u8"
    },
    {
      "name": "9",
      "slug": "9",
      "serverName": "Vietsub #1",
      "source": "ophim",
      "embedUrl": "https://vip.opstream90.com/share/133b5f08ade8b354bfd42b98c629ef05",
      "m3u8Url": "https://vip.opstream90.com/20260427/30350_133b5f08/index.m3u8"
    },
    {
      "name": "10",
      "slug": "10",
      "serverName": "Vietsub #1",
      "source": "ophim",
      "embedUrl": "https://vip.opstream90.com/share/768b2f133c3ea3ca2db797f5aa593417",
      "m3u8Url": "https://vip.opstream90.com/20260427/30351_768b2f13/index.m3u8"
    },
    {
      "name": "11",
      "slug": "11",
      "serverName": "Vietsub #1",
      "source": "ophim",
      "embedUrl": "https://vip.opstream90.com/share/e1b0e6b958ea38f4dae5f9d24730ef05",
      "m3u8Url": "https://vip.opstream90.com/20260428/30404_e1b0e6b9/index.m3u8"
    },
    {
      "name": "12",
      "slug": "12",
      "serverName": "Vietsub #1",
      "source": "ophim",
      "embedUrl": "https://vip.opstream90.com/share/e6c439226a0bde3e060ac5ce39b7d0f2",
      "m3u8Url": "https://vip.opstream90.com/20260428/30405_e6c43922/index.m3u8"
    },
    {
      "name": "13",
      "slug": "13",
      "serverName": "Vietsub #1",
      "source": "ophim",
      "embedUrl": "https://vip.opstream90.com/share/08d18210f962e39780ba7f1e45d51c7c",
      "m3u8Url": "https://vip.opstream90.com/20260429/30469_08d18210/index.m3u8"
    },
    {
      "name": "14",
      "slug": "14",
      "serverName": "Vietsub #1",
      "source": "ophim",
      "embedUrl": "https://vip.opstream90.com/share/bd50f363001990ee1fe5d798702b1d5b",
      "m3u8Url": "https://vip.opstream90.com/20260429/30470_bd50f363/index.m3u8"
    },
    {
      "name": "15",
      "slug": "15",
      "serverName": "Vietsub #1",
      "source": "ophim",
      "embedUrl": "https://vip.opstream90.com/share/2f201f1f5c6089c6ceb7086dd22d6447",
      "m3u8Url": "https://vip.opstream90.com/20260503/30891_2f201f1f/index.m3u8"
    },
    {
      "name": "16",
      "slug": "16",
      "serverName": "Vietsub #1",
      "source": "ophim",
      "embedUrl": "https://vip.opstream90.com/share/954f36b80ed21a866f1d1f4644d2ce50",
      "m3u8Url": "https://vip.opstream90.com/20260430/30621_954f36b8/index.m3u8"
    },
    {
      "name": "17",
      "slug": "17",
      "serverName": "Vietsub #1",
      "source": "ophim",
      "embedUrl": "https://vip.opstream90.com/share/a5819c80f61198eabf3d3ffceec595de",
      "m3u8Url": "https://vip.opstream90.com/20260501/30712_a5819c80/index.m3u8"
    },
    {
      "name": "18",
      "slug": "18",
      "serverName": "Vietsub #1",
      "source": "ophim",
      "embedUrl": "https://vip.opstream90.com/share/0898bae5662b8c4a9cd8ea2db1fa7ee4",
      "m3u8Url": "https://vip.opstream90.com/20260501/30713_0898bae5/index.m3u8"
    },
    {
      "name": "19",
      "slug": "19",
      "serverName": "Vietsub #1",
      "source": "ophim",
      "embedUrl": "https://vip.opstream90.com/share/18c9da69761a42ae620d9e9b0a57eb56",
      "m3u8Url": "https://vip.opstream90.com/20260502/30775_18c9da69/index.m3u8"
    },
    {
      "name": "20",
      "slug": "20",
      "serverName": "Vietsub #1",
      "source": "ophim",
      "embedUrl": "https://vip.opstream90.com/share/f1a90e1c055459c26e3280c607f8fe5e",
      "m3u8Url": "https://vip.opstream90.com/20260502/30776_f1a90e1c/index.m3u8"
    },
    {
      "name": "21",
      "slug": "21",
      "serverName": "Vietsub #1",
      "source": "ophim",
      "embedUrl": "https://vip.opstream90.com/share/e8d6b501bfa2981bd4c4a7a2eb822b28",
      "m3u8Url": "https://vip.opstream90.com/20260503/30870_e8d6b501/index.m3u8"
    },
    {
      "name": "22",
      "slug": "22",
      "serverName": "Vietsub #1",
      "source": "ophim",
      "embedUrl": "https://vip.opstream90.com/share/03ce0331cbd983f1689e1eea65561cac",
      "m3u8Url": "https://vip.opstream90.com/20260503/30871_03ce0331/index.m3u8"
    },
    {
      "name": "23",
      "slug": "23",
      "serverName": "Vietsub #1",
      "source": "ophim",
      "embedUrl": "https://vip.opstream90.com/share/bdba92535c1d9e8d4c4bf739243bb546",
      "m3u8Url": "https://vip.opstream90.com/20260504/30945_bdba9253/index.m3u8"
    },
    {
      "name": "24",
      "slug": "24",
      "serverName": "Vietsub #1",
      "source": "ophim",
      "embedUrl": "https://vip.opstream90.com/share/6540f6ffc2838caab9e0eba4c30ad7d8",
      "m3u8Url": "https://vip.opstream90.com/20260504/30946_6540f6ff/index.m3u8"
    },
    {
      "name": "25",
      "slug": "25",
      "serverName": "Vietsub #1",
      "source": "ophim",
      "embedUrl": "https://vip.opstream90.com/share/712c755bf49c37568c2a9934f32e6155",
      "m3u8Url": "https://vip.opstream90.com/20260505/31081_712c755b/index.m3u8"
    },
    {
      "name": "26",
      "slug": "26",
      "serverName": "Vietsub #1",
      "source": "ophim",
      "embedUrl": "https://vip.opstream90.com/share/19b6f0e016cb381b848ea23326085151",
      "m3u8Url": "https://vip.opstream90.com/20260505/31082_19b6f0e0/index.m3u8"
    },
    {
      "name": "27",
      "slug": "27",
      "serverName": "Vietsub #1",
      "source": "ophim",
      "embedUrl": "https://vip.opstream90.com/share/6784ac07a6aeb1433c961ace509971d0",
      "m3u8Url": "https://vip.opstream90.com/20260506/31186_6784ac07/index.m3u8"
    },
    {
      "name": "28",
      "slug": "28",
      "serverName": "Vietsub #1",
      "source": "ophim",
      "embedUrl": "https://vip.opstream90.com/share/e5654b80531b9a7338900193f90fbba5",
      "m3u8Url": "https://vip.opstream90.com/20260507/31228_e5654b80/index.m3u8"
    },
    {
      "name": "29",
      "slug": "29",
      "serverName": "Vietsub #1",
      "source": "ophim",
      "embedUrl": "https://vip.opstream90.com/share/a9dcc146714bd053238b84413ef7a3ff",
      "m3u8Url": "https://vip.opstream90.com/20260508/31417_a9dcc146/index.m3u8"
    },
    {
      "name": "30",
      "slug": "30",
      "serverName": "Vietsub #1",
      "source": "ophim",
      "embedUrl": "https://vip.opstream90.com/share/54a96ac32645d07ae686344a55414be1",
      "m3u8Url": "https://vip.opstream90.com/20260509/31469_54a96ac3/index.m3u8"
    },
    {
      "name": "31",
      "slug": "31",
      "serverName": "Vietsub #1",
      "source": "ophim",
      "embedUrl": "https://vip.opstream90.com/share/1504d56c70e614417b8d1aec1090fec5",
      "m3u8Url": "https://vip.opstream90.com/20260509/31470_1504d56c/index.m3u8"
    },
    {
      "name": "32",
      "slug": "32",
      "serverName": "Vietsub #1",
      "source": "ophim",
      "embedUrl": "https://vip.opstream90.com/share/1f79c37c38ef31e2174277b34e5aa64b",
      "m3u8Url": "https://vip.opstream90.com/20260510/31493_1f79c37c/index.m3u8"
    },
    {
      "name": "33",
      "slug": "33",
      "serverName": "Vietsub #1",
      "source": "ophim",
      "embedUrl": "https://vip.opstream90.com/share/db07748a120b8752dcac49ddfe281b71",
      "m3u8Url": "https://vip.opstream90.com/20260510/31494_db07748a/index.m3u8"
    },
    {
      "name": "34",
      "slug": "34",
      "serverName": "Vietsub #1",
      "source": "ophim",
      "embedUrl": "https://vip.opstream90.com/share/0e6175061abc25d19ad94fdf84a63ef6",
      "m3u8Url": "https://vip.opstream90.com/20260511/31538_0e617506/index.m3u8"
    },
    {
      "name": "35",
      "slug": "35",
      "serverName": "Vietsub #1",
      "source": "ophim",
      "embedUrl": "https://vip.opstream90.com/share/22b29bedd9bb2e315384e250d0a52d33",
      "m3u8Url": "https://vip.opstream90.com/20260511/31539_22b29bed/index.m3u8"
    },
    {
      "name": "36",
      "slug": "36",
      "serverName": "Vietsub #1",
      "source": "ophim",
      "embedUrl": "https://vip.opstream90.com/share/b16a06a5ea94028944a81ad5bbdbb8ca",
      "m3u8Url": "https://vip.opstream90.com/20260511/31540_b16a06a5/index.m3u8"
    },
    {
      "name": "37",
      "slug": "37",
      "serverName": "Vietsub #1",
      "source": "ophim",
      "embedUrl": "https://vip.opstream90.com/share/c8c1efaca9730df9826ea5f5bd72d025",
      "m3u8Url": "https://vip.opstream90.com/20260511/31541_c8c1efac/index.m3u8"
    },
    {
      "name": "38",
      "slug": "38",
      "serverName": "Vietsub #1",
      "source": "ophim",
      "embedUrl": "https://vip.opstream90.com/share/83606b4a6a0750fab695d8338a14844b",
      "m3u8Url": "https://vip.opstream90.com/20260511/31542_83606b4a/index.m3u8"
    },
    {
      "name": "39",
      "slug": "39",
      "serverName": "Vietsub #1",
      "source": "ophim",
      "embedUrl": "https://vip.opstream90.com/share/0628fc4708a87a5ad6fa86481d86836b",
      "m3u8Url": "https://vip.opstream90.com/20260511/31544_0628fc47/index.m3u8"
    },
    {
      "name": "40",
      "slug": "40",
      "serverName": "Vietsub #1",
      "source": "ophim",
      "embedUrl": "https://vip.opstream90.com/share/5cfcbafd768519bce51371aae5cac8fb",
      "m3u8Url": "https://vip.opstream90.com/20260511/31543_5cfcbafd/index.m3u8"
    },
    {
      "name": "1",
      "slug": "1",
      "serverName": "Thuyết Minh #1",
      "source": "ophim",
      "embedUrl": "https://vip.opstream90.com/share/d6de3681d8f3827433a7f8c54bbd5a81",
      "m3u8Url": "https://vip.opstream90.com/20260425/30206_d6de3681/index.m3u8"
    },
    {
      "name": "2",
      "slug": "2",
      "serverName": "Thuyết Minh #1",
      "source": "ophim",
      "embedUrl": "https://vip.opstream90.com/share/465c005d04204f859d0080c915f744b3",
      "m3u8Url": "https://vip.opstream90.com/20260425/30207_465c005d/index.m3u8"
    },
    {
      "name": "3",
      "slug": "3",
      "serverName": "Thuyết Minh #1",
      "source": "ophim",
      "embedUrl": "https://vip.opstream90.com/share/2947f6c206cc56866a88cc47130625d7",
      "m3u8Url": "https://vip.opstream90.com/20260425/30208_2947f6c2/index.m3u8"
    },
    {
      "name": "4",
      "slug": "4",
      "serverName": "Thuyết Minh #1",
      "source": "ophim",
      "embedUrl": "https://vip.opstream90.com/share/0f47d8af9d0abe580c26d8551f4071f1",
      "m3u8Url": "https://vip.opstream90.com/20260425/30209_0f47d8af/index.m3u8"
    },
    {
      "name": "5",
      "slug": "5",
      "serverName": "Thuyết Minh #1",
      "source": "ophim",
      "embedUrl": "https://vip.opstream90.com/share/c01afd54a92fec65ed6d29f568cebd48",
      "m3u8Url": "https://vip.opstream90.com/20260425/30210_c01afd54/index.m3u8"
    },
    {
      "name": "6",
      "slug": "6",
      "serverName": "Thuyết Minh #1",
      "source": "ophim",
      "embedUrl": "https://vip.opstream90.com/share/0fb14adee231d12b0f1465448626e6f7",
      "m3u8Url": "https://vip.opstream90.com/20260425/30211_0fb14ade/index.m3u8"
    },
    {
      "name": "7",
      "slug": "7",
      "serverName": "Thuyết Minh #1",
      "source": "ophim",
      "embedUrl": "https://vip.opstream90.com/share/4992f85f02e4d718826650c96219875d",
      "m3u8Url": "https://vip.opstream90.com/20260426/30274_4992f85f/index.m3u8"
    },
    {
      "name": "8",
      "slug": "8",
      "serverName": "Thuyết Minh #1",
      "source": "ophim",
      "embedUrl": "https://vip.opstream90.com/share/5131f6caead4314643b671b624714d94",
      "m3u8Url": "https://vip.opstream90.com/20260426/30275_5131f6ca/index.m3u8"
    },
    {
      "name": "9",
      "slug": "9",
      "serverName": "Thuyết Minh #1",
      "source": "ophim",
      "embedUrl": "https://vip.opstream90.com/share/5646dfcf5046a6c1b4014ee53d9d614d",
      "m3u8Url": "https://vip.opstream90.com/20260427/30349_5646dfcf/index.m3u8"
    },
    {
      "name": "10",
      "slug": "10",
      "serverName": "Thuyết Minh #1",
      "source": "ophim",
      "embedUrl": "https://vip.opstream90.com/share/650bbf5d3ffa2b7d9b8b36d62d667ced",
      "m3u8Url": "https://vip.opstream90.com/20260427/30352_650bbf5d/index.m3u8"
    },
    {
      "name": "11",
      "slug": "11",
      "serverName": "Thuyết Minh #1",
      "source": "ophim",
      "embedUrl": "https://vip.opstream90.com/share/e3036fb3e0fd60ba20772f6325fa8f60",
      "m3u8Url": "https://vip.opstream90.com/20260428/30403_e3036fb3/index.m3u8"
    },
    {
      "name": "12",
      "slug": "12",
      "serverName": "Thuyết Minh #1",
      "source": "ophim",
      "embedUrl": "https://vip.opstream90.com/share/af4d3ce5d7a2e6955130f2b2720d0873",
      "m3u8Url": "https://vip.opstream90.com/20260428/30406_af4d3ce5/index.m3u8"
    },
    {
      "name": "13",
      "slug": "13",
      "serverName": "Thuyết Minh #1",
      "source": "ophim",
      "embedUrl": "https://vip.opstream90.com/share/8d6fd71d81a15e4faaa1078845097647",
      "m3u8Url": "https://vip.opstream90.com/20260429/30471_8d6fd71d/index.m3u8"
    },
    {
      "name": "14",
      "slug": "14",
      "serverName": "Thuyết Minh #1",
      "source": "ophim",
      "embedUrl": "https://vip.opstream90.com/share/4da79a45c5e5c96760be4d8673c0aefd",
      "m3u8Url": "https://vip.opstream90.com/20260429/30472_4da79a45/index.m3u8"
    },
    {
      "name": "16",
      "slug": "16",
      "serverName": "Thuyết Minh #1",
      "source": "ophim",
      "embedUrl": "https://vip.opstream90.com/share/7ffd8ebf0f316956c827375501307e10",
      "m3u8Url": "https://vip.opstream90.com/20260430/30623_7ffd8ebf/index.m3u8"
    },
    {
      "name": "16",
      "slug": "16",
      "serverName": "Thuyết Minh #1",
      "source": "ophim",
      "embedUrl": "https://vip.opstream90.com/share/c02d80d1ecf882ebc1c05beeb11adbca",
      "m3u8Url": "https://vip.opstream90.com/20260430/30615_c02d80d1/index.m3u8"
    },
    {
      "name": "17",
      "slug": "17",
      "serverName": "Thuyết Minh #1",
      "source": "ophim",
      "embedUrl": "https://vip.opstream90.com/share/5b768a6943e0867ed0a8825406908b91",
      "m3u8Url": "https://vip.opstream90.com/20260501/30711_5b768a69/index.m3u8"
    },
    {
      "name": "18",
      "slug": "18",
      "serverName": "Thuyết Minh #1",
      "source": "ophim",
      "embedUrl": "https://vip.opstream90.com/share/7b3678e568c812fa368f74671eaac799",
      "m3u8Url": "https://vip.opstream90.com/20260501/30714_7b3678e5/index.m3u8"
    },
    {
      "name": "19",
      "slug": "19",
      "serverName": "Thuyết Minh #1",
      "source": "ophim",
      "embedUrl": "https://vip.opstream90.com/share/420e7a59c4ccc0dbeb1d58e2126c42d5",
      "m3u8Url": "https://vip.opstream90.com/20260502/30779_420e7a59/index.m3u8"
    },
    {
      "name": "20",
      "slug": "20",
      "serverName": "Thuyết Minh #1",
      "source": "ophim",
      "embedUrl": "https://vip.opstream90.com/share/23dd1052628bd01a4146b88619ec601e",
      "m3u8Url": "https://vip.opstream90.com/20260502/30780_23dd1052/index.m3u8"
    },
    {
      "name": "21",
      "slug": "21",
      "serverName": "Thuyết Minh #1",
      "source": "ophim",
      "embedUrl": "https://vip.opstream90.com/share/f81e312ca3fbd61d515bb65deac0259c",
      "m3u8Url": "https://vip.opstream90.com/20260503/30872_f81e312c/index.m3u8"
    },
    {
      "name": "22",
      "slug": "22",
      "serverName": "Thuyết Minh #1",
      "source": "ophim",
      "embedUrl": "https://vip.opstream90.com/share/f8936fbd065f5b9fdb3149eaba9665df",
      "m3u8Url": "https://vip.opstream90.com/20260503/30873_f8936fbd/index.m3u8"
    },
    {
      "name": "23",
      "slug": "23",
      "serverName": "Thuyết Minh #1",
      "source": "ophim",
      "embedUrl": "https://vip.opstream90.com/share/f23a13a09954dada8fad3e0691dfcf0f",
      "m3u8Url": "https://vip.opstream90.com/20260504/30947_f23a13a0/index.m3u8"
    },
    {
      "name": "24",
      "slug": "24",
      "serverName": "Thuyết Minh #1",
      "source": "ophim",
      "embedUrl": "https://vip.opstream90.com/share/a41b7c188df8001c036825089b562709",
      "m3u8Url": "https://vip.opstream90.com/20260504/30948_a41b7c18/index.m3u8"
    },
    {
      "name": "25",
      "slug": "25",
      "serverName": "Thuyết Minh #1",
      "source": "ophim",
      "embedUrl": "https://vip.opstream90.com/share/808c180bdf9dbb4aa16f114e795a59e8",
      "m3u8Url": "https://vip.opstream90.com/20260505/31087_808c180b/index.m3u8"
    },
    {
      "name": "26",
      "slug": "26",
      "serverName": "Thuyết Minh #1",
      "source": "ophim",
      "embedUrl": "https://vip.opstream90.com/share/31512882b56aad75c6cce98a40cbafe4",
      "m3u8Url": "https://vip.opstream90.com/20260505/31088_31512882/index.m3u8"
    },
    {
      "name": "27",
      "slug": "27",
      "serverName": "Thuyết Minh #1",
      "source": "ophim",
      "embedUrl": "https://vip.opstream90.com/share/16a153a27394122922a55fb102f602e3",
      "m3u8Url": "https://vip.opstream90.com/20260506/31195_16a153a2/index.m3u8"
    },
    {
      "name": "28",
      "slug": "28",
      "serverName": "Thuyết Minh #1",
      "source": "ophim",
      "embedUrl": "https://vip.opstream90.com/share/47e7fdb0ab1113aaef1f5029de4792b0",
      "m3u8Url": "https://vip.opstream90.com/20260508/31396_47e7fdb0/index.m3u8"
    },
    {
      "name": "29",
      "slug": "29",
      "serverName": "Thuyết Minh #1",
      "source": "ophim",
      "embedUrl": "https://vip.opstream90.com/share/e9e94782c7568e898a1ed151bb8b401b",
      "m3u8Url": "https://vip.opstream90.com/20260508/31405_e9e94782/index.m3u8"
    },
    {
      "name": "30",
      "slug": "30",
      "serverName": "Thuyết Minh #1",
      "source": "ophim",
      "embedUrl": "https://vip.opstream90.com/share/435c53251dc1f41d8d6b80f8592f6650",
      "m3u8Url": "https://vip.opstream90.com/20260509/31467_435c5325/index.m3u8"
    },
    {
      "name": "31",
      "slug": "31",
      "serverName": "Thuyết Minh #1",
      "source": "ophim",
      "embedUrl": "https://vip.opstream90.com/share/90a562851e9222030339fcf2960c15e9",
      "m3u8Url": "https://vip.opstream90.com/20260509/31468_90a56285/index.m3u8"
    },
    {
      "name": "32",
      "slug": "32",
      "serverName": "Thuyết Minh #1",
      "source": "ophim",
      "embedUrl": "https://vip.opstream90.com/share/348a43bb0eadc84915bcd8d95f373b0f",
      "m3u8Url": "https://vip.opstream90.com/20260510/31495_348a43bb/index.m3u8"
    },
    {
      "name": "33",
      "slug": "33",
      "serverName": "Thuyết Minh #1",
      "source": "ophim",
      "embedUrl": "https://vip.opstream90.com/share/4a0d4e0d21df28d99ff95e6bd9ca0acc",
      "m3u8Url": "https://vip.opstream90.com/20260510/31496_4a0d4e0d/index.m3u8"
    },
    {
      "name": "34",
      "slug": "34",
      "serverName": "Thuyết Minh #1",
      "source": "ophim",
      "embedUrl": "https://vip.opstream90.com/share/c748d08c853dce45d5413435a4c3aa10",
      "m3u8Url": "https://vip.opstream90.com/20260511/31545_c748d08c/index.m3u8"
    },
    {
      "name": "35",
      "slug": "35",
      "serverName": "Thuyết Minh #1",
      "source": "ophim",
      "embedUrl": "https://vip.opstream90.com/share/c695c406dd17d2fc9dbfe917adaf9e33",
      "m3u8Url": "https://vip.opstream90.com/20260511/31546_c695c406/index.m3u8"
    },
    {
      "name": "36",
      "slug": "36",
      "serverName": "Thuyết Minh #1",
      "source": "ophim",
      "embedUrl": "https://vip.opstream90.com/share/b849b10a4aadcab1172ee5c75838ae3f",
      "m3u8Url": "https://vip.opstream90.com/20260511/31547_b849b10a/index.m3u8"
    },
    {
      "name": "37",
      "slug": "37",
      "serverName": "Thuyết Minh #1",
      "source": "ophim",
      "embedUrl": "https://vip.opstream90.com/share/0422806ff5b272edd98b2e11a2fc3a4f",
      "m3u8Url": "https://vip.opstream90.com/20260511/31548_0422806f/index.m3u8"
    },
    {
      "name": "38",
      "slug": "38",
      "serverName": "Thuyết Minh #1",
      "source": "ophim",
      "embedUrl": "https://vip.opstream90.com/share/3f6ef69d17c6561909c684b8189fe349",
      "m3u8Url": "https://vip.opstream90.com/20260511/31549_3f6ef69d/index.m3u8"
    },
    {
      "name": "39",
      "slug": "39",
      "serverName": "Thuyết Minh #1",
      "source": "ophim",
      "embedUrl": "https://vip.opstream90.com/share/09c039292630f588a0528fb457d63c7e",
      "m3u8Url": "https://vip.opstream90.com/20260511/31551_09c03929/index.m3u8"
    },
    {
      "name": "40",
      "slug": "40",
      "serverName": "Thuyết Minh #1",
      "source": "ophim",
      "embedUrl": "https://vip.opstream90.com/share/4c7e17f10bce99f0c3df0f414eb9165c",
      "m3u8Url": "https://vip.opstream90.com/20260511/31552_4c7e17f1/index.m3u8"
    }
  ],
  "sources": [
    {
      "source": "ophim",
      "slug": "giai-ngau-thien-thanh",
      "episodeCount": 80,
      "priority": 0
    }
  ],
  "_priority": 0
}