{
  "id": "into-the-wind-12181681",
  "source": "nguonc",
  "slug": "hoa-vao-gio",
  "name": "Hòa Vào Gió",
  "originName": "Into the Wind",
  "posterUrl": "https://phim.nguonc.com/public/images/Film/9YUOSQevLpvWOiZYcrDyyHcvNqD.jpg",
  "thumbUrl": "https://phim.nguonc.com/public/images/Film/y2lylZT9Czehopiln1D9hc1Bb84.jpg",
  "status": "completed",
  "episodeCurrent": "FULL",
  "categories": [],
  "countries": [],
  "description": "Sóng, nắng và đam mê đang chờ đón khi nàng tiểu thư tuổi teen trải qua mối tình đầu với một huấn luyện viên lướt ván diều phóng khoáng ở khu nghỉ mát bên bờ biển.",
  "quality": "HD",
  "episodes": [
    {
      "name": "Full",
      "slug": "tap-full",
      "serverName": "Vietsub #1",
      "source": "nguonc",
      "embedUrl": "https://embed18.streamc.xyz/embed.php?hash=bba279737610e06788d30acbe7792b99",
      "m3u8Url": "https://sing.phimmoi.net/bba279737610e06788d30acbe7792b99/hls.m3u8"
    }
  ],
  "sources": [
    {
      "source": "nguonc",
      "slug": "hoa-vao-gio",
      "episodeCount": 1,
      "priority": 2
    }
  ],
  "_priority": 2
}